odoo8_addon_partner_second_lastname-8.0.4.1.0.99.dev6-py2.7-nspkg.pth
odoo8_addon_partner_second_lastname-8.0.4.1.0.99.dev6.dist-info/METADATA
odoo8_addon_partner_second_lastname-8.0.4.1.0.99.dev6.dist-info/RECORD
odoo8_addon_partner_second_lastname-8.0.4.1.0.99.dev6.dist-info/WHEEL
odoo8_addon_partner_second_lastname-8.0.4.1.0.99.dev6.dist-info/namespace_packages.txt
odoo8_addon_partner_second_lastname-8.0.4.1.0.99.dev6.dist-info/top_level.txt
odoo_addons/partner_second_lastname/README.rst
odoo_addons/partner_second_lastname/__init__.py
odoo_addons/partner_second_lastname/__openerp__.py
odoo_addons/partner_second_lastname/i18n/de.po
odoo_addons/partner_second_lastname/i18n/es.po
odoo_addons/partner_second_lastname/i18n/eu.po
odoo_addons/partner_second_lastname/i18n/fi.po
odoo_addons/partner_second_lastname/i18n/it.po
odoo_addons/partner_second_lastname/i18n/partner_second_lastname.pot
odoo_addons/partner_second_lastname/i18n/sl.po
odoo_addons/partner_second_lastname/models/__init__.py
odoo_addons/partner_second_lastname/models/base_config_settings.py
odoo_addons/partner_second_lastname/models/res_partner.py
odoo_addons/partner_second_lastname/static/description/icon.png
odoo_addons/partner_second_lastname/tests/__init__.py
odoo_addons/partner_second_lastname/tests/test_name.py
odoo_addons/partner_second_lastname/tests/test_onchange.py
odoo_addons/partner_second_lastname/views/res_partner.xml
odoo_addons/partner_second_lastname/views/res_user.xml
