Metadata-Version: 2.1
Name: odoo8-addon-partner-second-lastname
Version: 8.0.4.1.0.99.dev6
Summary: Have split first and second lastnames
Home-page: https://grupoesoc.es
Author: Grupo ESOC Ingeniería de Servicios, Odoo Community Association (OCA)
Author-email: support@odoo-community.org
License: AGPL-3
Platform: UNKNOWN
Classifier: Programming Language :: Python
Classifier: Framework :: Odoo
Classifier: License :: OSI Approved :: GNU Affero General Public License v3
Requires-Python: ~=2.7
Requires-Dist: odoo8-addon-partner-firstname
Requires-Dist: odoo (<9.0a,>=8.0a)
